LICENSE
README.md
nautobot_plugin_chatops_meraki/__init__.py
nautobot_plugin_chatops_meraki/static/nautobot_meraki/meraki.png
nautobot_plugin_chatops_meraki/tests/__init__.py
nautobot_plugin_chatops_meraki/tests/test_basic.py
nautobot_plugin_chatops_meraki/tests/test_utils.py
nautobot_plugin_chatops_meraki/utils.py
nautobot_plugin_chatops_meraki/worker.py
nautobot_chatops_meraki-1.2.0.dist-info/entry_points.txt
nautobot_chatops_meraki-1.2.0.dist-info/LICENSE
nautobot_chatops_meraki-1.2.0.dist-info/WHEEL
nautobot_chatops_meraki-1.2.0.dist-info/METADATA
nautobot_chatops_meraki-1.2.0.dist-info/RECORD
