Metadata-Version: 2.1
Name: nautobot-chatops-meraki
Version: 1.2.0
Summary: Nautobot Chatops Meraki
Home-page: https://github.com/networktocode-llc/nautobot-plugin-chatops-meraki
License: Apache-2.0
Keywords: nautobot,nautobot-plugin,nautobot-chatops-plugin
Author: Network to Code, LLC
Author-email: info@networktocode.com
Requires-Python: >=3.7,<4.0
Classifier: License :: OSI Approved :: Apache Software License
Classifier: Programming Language :: Python :: 3
Classifier: Programming Language :: Python :: 3.10
Classifier: Programming Language :: Python :: 3.7
Classifier: Programming Language :: Python :: 3.8
Classifier: Programming Language :: Python :: 3.9
Requires-Dist: meraki (>=1.7.2,<2.0.0)
Requires-Dist: nautobot-chatops (>=1.1.0,<2.0.0)
Project-URL: Repository, https://github.com/networktocode-llc/nautobot-plugin-chatops-meraki
